{
  "schemaVersion": 2,
  "id": "roundabout",
  "packId": null,
  "hidden": false,
  "dirtChunks": true,
  "name": "Roundabout",
  "width": 160,
  "depth": 160,
  "defaultTerrainType": "packed_dirt",
  "borderTerrainType": "packed_dirt",
  "wear": {
    "enabled": true,
    "source": "aiPath",
    "alphaBreakup": 0.28,
    "width": 4,
    "intensity": 0.8,
    "laneSpacing": 2,
    "pathWander": 0.7,
    "edgeSoftness": 1,
    "secondaryPathCount": 60,
    "secondaryPathStrength": 0.8,
    "secondaryPathSpacing": 0.04,
    "seed": 1337
  },
  "features": [
    {
      "type": "meshGrid",
      "regional": false,
      "centerX": 0,
      "centerZ": 0,
      "angle": 0,
      "width": 160,
      "depth": 160,
      "cols": 9,
      "rows": 9,
      "heights": [
        5,
        5,
        5,
        5,
        0,
        0,
        0,
        0,
        30,
        5,
        5,
        5,
        5,
        0,
        0,
        0,
        0,
        0,
        0,
        0,
        0,
        0,
        0,
        0,
        0,
        0,
        0,
        0,
        0,
        0,
        0,
        0,
        0,
        0,
        0,
        0,
        0,
        0,
        0,
        0,
        0,
        0,
        0,
        0,
        0,
        0,
        0,
        0,
        0,
        0,
        0,
        0,
        0,
        0,
        0,
        0,
        0,
        0,
        0,
        0,
        0,
        0,
        0,
        0,
        10,
        0,
        0,
        0,
        0,
        0,
        0,
        0,
        3,
        0,
        0,
        0,
        0,
        0,
        0,
        0,
        0
      ],
      "smoothing": 0.75
    },
    {
      "type": "hill",
      "centerX": -1.793770289227772,
      "centerZ": -9.839531435729732,
      "radiusX": 22,
      "radiusZ": 22,
      "angle": 0,
      "height": -5,
      "waterLevelOffset": 3.6,
      "terrainType": "water"
    },
    {
      "type": "terrain",
      "shape": "circle",
      "centerX": -2.5178802461819787,
      "centerZ": -2.0091894184601458,
      "terrainType": "rocky",
      "width": 80,
      "depth": 80,
      "rotation": 0,
      "blendWidth": 11
    },
    {
      "type": "terrainPath",
      "points": [],
      "width": 16,
      "blendWidth": 2,
      "cornerRadius": 5,
      "closed": false,
      "terrainType": "mud"
    },
    {
      "type": "terrainPath",
      "points": [
        {
          "x": -54.54864213238384,
          "z": 6.7263899603297475
        },
        {
          "x": -48.639042584284915,
          "z": 32.82413743715108
        },
        {
          "x": -35.907317335425546,
          "z": 44.601233385259114
        },
        {
          "x": -14.528965853461257,
          "z": 51.89870348761484
        },
        {
          "x": 29.593911142567524,
          "z": 54.77273201694353
        },
        {
          "x": 41.42,
          "z": 54.67
        },
        {
          "x": 48.58,
          "z": 43.4
        },
        {
          "x": 53.64,
          "z": 28.58
        },
        {
          "x": 54.66,
          "z": 13.21
        },
        {
          "x": 52.7,
          "z": -12.71
        },
        {
          "x": 46.95,
          "z": -26.61
        },
        {
          "x": 42.8,
          "z": -36.03
        },
        {
          "x": 27.56,
          "z": -54.8
        },
        {
          "x": 2.51,
          "z": -57.37
        },
        {
          "x": -25.54,
          "z": -57.46
        },
        {
          "x": -45.22,
          "z": -44.79
        },
        {
          "x": -69.29,
          "z": -54.02
        },
        {
          "x": -64.80789611686491,
          "z": -61.72635238088237
        },
        {
          "x": -55.694422163652476,
          "z": -70.20669265606905
        },
        {
          "x": -45.27800091705371,
          "z": -72.83438365242745
        },
        {
          "x": -29.332744224341205,
          "z": -73.87608503138533
        },
        {
          "x": -9.736749943450956,
          "z": -76.17083543237295
        },
        {
          "x": 4.6730457523926745,
          "z": -74.94870892660163
        },
        {
          "x": 29.236901041546407,
          "z": -70.88438029415404
        },
        {
          "x": 58.82,
          "z": -66.56
        },
        {
          "x": 73.18,
          "z": -38.5
        },
        {
          "x": 74.8832689123517,
          "z": 4.068355075282158
        },
        {
          "x": 73.87013818657931,
          "z": 35.97002756907336
        },
        {
          "x": 68.18,
          "z": 66.41
        },
        {
          "x": 48.518835519845915,
          "z": 72.07158303107487
        },
        {
          "x": 31.109903755858344,
          "z": 71.05693534658529
        },
        {
          "x": 13.02648238913468,
          "z": 72.40747254506276
        },
        {
          "x": -10.142997361189309,
          "z": 72.80197141370294
        },
        {
          "x": -28.826537700211972,
          "z": 70.67810615411611
        },
        {
          "x": -44.620394655455655,
          "z": 63.209470420539006
        },
        {
          "x": -64.90399759605717,
          "z": 53.22809814332781
        },
        {
          "x": -68.77002350983092,
          "z": 31.65324957883449
        },
        {
          "x": -71.08655906485153,
          "z": 7.346688733488136
        },
        {
          "x": -75.63229172745392,
          "z": -13.213342935317712
        },
        {
          "x": -72.87,
          "z": -27.31
        },
        {
          "x": -60.07,
          "z": -18.1
        }
      ],
      "width": 13.5,
      "blendWidth": 2,
      "cornerRadius": 4,
      "closed": true,
      "terrainType": "rocky"
    },
    {
      "type": "polyWall",
      "points": [
        {
          "x": -80,
          "z": -39.554606921500465,
          "radius": 0
        },
        {
          "x": -39.10954193436464,
          "z": -33.607184900692125,
          "radius": 5
        },
        {
          "x": -10.48834269684913,
          "z": -47.66183569470073,
          "radius": 5
        },
        {
          "x": 18.804263513613552,
          "z": -43.63739939604245,
          "radius": 5
        },
        {
          "x": 37.563221721157724,
          "z": -3.0683378453681343,
          "radius": 0
        },
        {
          "x": 40.25742887077178,
          "z": 42.405085821426624,
          "radius": 30
        },
        {
          "x": -33.852165396049074,
          "z": 32.39416113207266,
          "radius": 0
        },
        {
          "x": -38.71212648665889,
          "z": 5.986987099721702,
          "radius": 5
        },
        {
          "x": -59.84670449162439,
          "z": -35.37158100305335,
          "radius": 5
        }
      ],
      "height": 2,
      "collisionHeight": 2,
      "thickness": 0.5,
      "friction": 0.05,
      "closed": false,
      "style": "black_yellow"
    },
    {
      "type": "polyWall",
      "points": [
        {
          "x": -52.884416698369755,
          "z": -59.83034601845331,
          "radius": 0
        },
        {
          "x": -21.256637867340686,
          "z": -68.81384277660298,
          "radius": 5
        },
        {
          "x": 17.05857325062442,
          "z": -66.0938945278568,
          "radius": 5
        },
        {
          "x": 52.955125121510726,
          "z": -48.39315986461364,
          "radius": 5
        },
        {
          "x": 64.80286895836093,
          "z": -5.310292323221788,
          "radius": 0
        },
        {
          "x": 59.3873958041587,
          "z": 66.12633290402385,
          "radius": 30
        },
        {
          "x": -10.330893988041254,
          "z": 61.002838480766684,
          "radius": 0
        },
        {
          "x": -40.56763093178419,
          "z": 55.93363387796591,
          "radius": 5,
          "smoothing": 1
        },
        {
          "x": -57.36027705754691,
          "z": 44.52390244596639,
          "radius": 5
        },
        {
          "x": -67.34763052336132,
          "z": -14.442202635803298,
          "radius": 5
        }
      ],
      "height": 2,
      "collisionHeight": 2,
      "thickness": 0.5,
      "friction": 0.05,
      "closed": false,
      "style": "black_yellow"
    },
    {
      "type": "checkpoint",
      "centerX": -68.74600857911666,
      "centerZ": 35.29449806806669,
      "heading": 3.141592653589793,
      "width": 12,
      "checkpointNumber": 1,
      "_altIndex": 0,
      "_altCount": 1
    },
    {
      "type": "checkpoint",
      "centerX": -48.05912847313498,
      "centerZ": 32.33789512695949,
      "heading": 0.3490658503988659,
      "width": 14.5,
      "checkpointNumber": 2,
      "_altIndex": 0,
      "_altCount": 1
    },
    {
      "type": "tent",
      "x": -56.57823005607039,
      "z": -8.687525083899466,
      "heading": 0.33161255787892263,
      "scale": 4,
      "color": "red"
    },
    {
      "type": "obstacle",
      "obstacleType": "barrel",
      "x": 31.944436124893652,
      "z": -19.912523908587936,
      "angle": 0,
      "scale": 1,
      "weight": 22,
      "color": "yellow"
    },
    {
      "type": "obstacle",
      "obstacleType": "barrel",
      "x": 44.34734057399772,
      "z": -29.193955215310375,
      "angle": 0,
      "scale": 1,
      "weight": 22,
      "color": "yellow"
    },
    {
      "type": "obstacle",
      "obstacleType": "barrel",
      "x": 24.438664102692876,
      "z": -44.56972530791364,
      "angle": 0,
      "scale": 1,
      "weight": 22,
      "color": "yellow"
    },
    {
      "type": "obstacle",
      "obstacleType": "barrel",
      "x": 38.288551720201625,
      "z": -47.198352764301106,
      "angle": 0,
      "scale": 1,
      "weight": 22,
      "color": "yellow"
    },
    {
      "type": "obstacle",
      "obstacleType": "barrel",
      "x": 33.82564666767186,
      "z": -26.633345536630564,
      "angle": 0,
      "scale": 1,
      "weight": 22,
      "color": "yellow"
    },
    {
      "type": "obstacle",
      "obstacleType": "barrel",
      "x": 56.17935732459101,
      "z": -17.447371073846412,
      "angle": 0,
      "scale": 1,
      "weight": 22,
      "color": "yellow"
    },
    {
      "type": "obstacle",
      "obstacleType": "barrel",
      "x": 51.17813011082835,
      "z": -8.461346623537466,
      "angle": 0,
      "scale": 1,
      "weight": 22,
      "color": "yellow"
    },
    {
      "type": "obstacle",
      "obstacleType": "barrel",
      "x": 47.78432974082573,
      "z": 4.873756454124731,
      "angle": 0,
      "scale": 1,
      "weight": 22,
      "color": "yellow"
    },
    {
      "type": "obstacle",
      "obstacleType": "softWall",
      "x": -79.58412633950918,
      "z": -48.164037567171675,
      "angle": 1.1868238913561442,
      "scale": 1,
      "weight": 80,
      "color": "red"
    },
    {
      "type": "obstacle",
      "obstacleType": "softWall",
      "x": -80,
      "z": -32.66474397946764,
      "angle": 2.3387411976724013,
      "scale": 1,
      "weight": 80,
      "color": "red"
    },
    {
      "type": "obstacle",
      "obstacleType": "softWall",
      "x": -74.5556646866551,
      "z": -35.112970632094616,
      "angle": 1.780235837034216,
      "scale": 1,
      "weight": 80,
      "color": "red"
    },
    {
      "type": "obstacle",
      "obstacleType": "softWall",
      "x": -73.44783963764534,
      "z": -42.6453636037061,
      "angle": 0.9424777960769379,
      "scale": 1,
      "weight": 80,
      "color": "red"
    },
    {
      "type": "checkpoint",
      "centerX": -57.201329599214304,
      "centerZ": -49.681801571309684,
      "heading": -2.007128639793479,
      "width": 17,
      "checkpointNumber": 3,
      "_altIndex": 0,
      "_altCount": 1
    },
    {
      "type": "checkpoint",
      "centerX": 64.48020645089656,
      "centerZ": -55.60581418086143,
      "heading": 0.4363323129985824,
      "width": 13,
      "checkpointNumber": 4,
      "_altIndex": 0,
      "_altCount": 1
    },
    {
      "type": "checkpoint",
      "centerX": 73.30497351455759,
      "centerZ": 30.603591729337232,
      "heading": 0,
      "width": 12,
      "checkpointNumber": 5,
      "_altIndex": 0,
      "_altCount": 1
    },
    {
      "type": "trackSign",
      "x": 72.83484508893648,
      "z": 35.529148549408916,
      "name": " Roundabout ",
      "rotation": 0,
      "contentType": "text",
      "brandImage": "energizer-racing.png",
      "background": "yellow",
      "primaryColor": "black",
      "scale": 2.2,
      "heightOffset": 5.1,
      "width": 8.5
    },
    {
      "type": "aiPath",
      "points": [
        {
          "x": 73.21,
          "z": 34.52
        },
        {
          "x": 64.36,
          "z": 69.43
        },
        {
          "x": -40.52,
          "z": 68.43
        },
        {
          "x": -66.44,
          "z": 46.13
        },
        {
          "x": -76.61,
          "z": -27.61
        },
        {
          "x": -67.23754057402562,
          "z": -26.13593651926483
        },
        {
          "x": -42.8,
          "z": 36.69
        },
        {
          "x": 5.21,
          "z": 52.4
        },
        {
          "x": 51.21,
          "z": 38.4
        },
        {
          "x": 46.5,
          "z": -29.9
        },
        {
          "x": 16.84,
          "z": -55.61
        },
        {
          "x": -41.09,
          "z": -50.23
        },
        {
          "x": -68.4,
          "z": -56.47
        },
        {
          "x": -35.73,
          "z": -74.89
        },
        {
          "x": 54.81,
          "z": -66.83
        },
        {
          "x": 68.75,
          "z": -46.74
        }
      ],
      "branches": []
    }
  ]
}